AUTHORS.rst
CONTRIBUTING.rst
HISTORY.rst
LICENSE
MANIFEST.in
README.rst
setup.cfg
setup.py
docs/Makefile
docs/authors.rst
docs/conf.py
docs/contributing.rst
docs/history.rst
docs/index.rst
docs/installation.rst
docs/make.bat
docs/readme.rst
docs/sqloose.rst
docs/usage.rst
docs/_build/html/_static/ajax-loader.gif
docs/_build/html/_static/comment-bright.png
docs/_build/html/_static/comment-close.png
docs/_build/html/_static/comment.png
docs/_build/html/_static/down-pressed.png
docs/_build/html/_static/down.png
docs/_build/html/_static/file.png
docs/_build/html/_static/minus.png
docs/_build/html/_static/plus.png
docs/_build/html/_static/up-pressed.png
docs/_build/html/_static/up.png
sqloose/__init__.py
sqloose/cli.py
sqloose/sqloose.py
sqloose.egg-info/PKG-INFO
sqloose.egg-info/SOURCES.txt
sqloose.egg-info/dependency_links.txt
sqloose.egg-info/entry_points.txt
sqloose.egg-info/not-zip-safe
sqloose.egg-info/requires.txt
sqloose.egg-info/top_level.txt
tests/__init__.py
tests/test_sqloose.py