Metadata-Version: 1.1
Name: sqloose
Version: 0.1.0
Summary: sqloose something
Home-page: https://github.com/oddacious/sqloose
Author: rdj
Author-email: fumble.to.victory@gmail.com
License: Apache Software License 2.0
Keywords: sqloose
Platform: UNKNOWN
Classifier: Development Status :: 2 - Pre-Alpha
Classifier: Intended Audience :: Developers
Classifier: License :: OSI Approved :: Apache Software License
Classifier: Natural Language :: English
Classifier: Programming Language :: Python :: 2
Classifier: Programming Language :: Python :: 2.6
Classifier: Programming Language :: Python :: 2.7
Classifier: Programming Language :: Python :: 3
Classifier: Programming Language :: Python :: 3.3
Classifier: Programming Language :: Python :: 3.4
Classifier: Programming Language :: Python :: 3.5
